vmware_fusion_mcp/__init__.py
vmware_fusion_mcp/server.py
vmware_fusion_mcp/vmware_client.py
vmware_fusion_mcp_server-0.1.5.dist-info/METADATA
vmware_fusion_mcp_server-0.1.5.dist-info/WHEEL
vmware_fusion_mcp_server-0.1.5.dist-info/entry_points.txt
vmware_fusion_mcp_server-0.1.5.dist-info/licenses/LICENSE
vmware_fusion_mcp_server-0.1.5.dist-info/RECORD
