Metadata-Version: 2.4
Name: vmware-fusion-mcp-server
Version: 0.1.5
Summary: A MCP server for managing VMware Fusion VMs via REST API
Project-URL: Homepage, https://github.com/yeahdongcn/vmware-fusion-mcp-server
Project-URL: Documentation, https://github.com/yeahdongcn/vmware-fusion-mcp-server#readme
Project-URL: Repository, https://github.com/yeahdongcn/vmware-fusion-mcp-server.git
Project-URL: Issues, https://github.com/yeahdongcn/vmware-fusion-mcp-server/issues
Project-URL: Changelog, https://github.com/yeahdongcn/vmware-fusion-mcp-server/releases
Author-email: Xiaodong Ye <yeahdongcn@gmail.com>
Maintainer-email: Xiaodong Ye <yeahdongcn@gmail.com>
License-Expression: MIT
License-File: LICENSE
Keywords: agents,ai,automation,fusion,mcp,model-context-protocol,vmware
Classifier: Development Status :: 4 - Beta
Classifier: Intended Audience :: Developers
Classifier: Intended Audience :: Information Technology
Classifier: Operating System :: OS Independent
Classifier: Programming Language :: Python :: 3
Classifier: Programming Language :: Python :: 3.10
Classifier: Programming Language :: Python :: 3.11
Classifier: Programming Language :: Python :: 3.12
Classifier: Programming Language :: Python :: 3.13
Classifier: Topic :: Scientific/Engineering :: Artificial Intelligence
Classifier: Topic :: Software Development :: Libraries :: Python Modules
Classifier: Topic :: System :: Systems Administration
Classifier: Topic :: Utilities
Requires-Python: >=3.10
Requires-Dist: fastmcp>=2.10.3
Requires-Dist: httpx>=0.28.1
Provides-Extra: dev
Requires-Dist: black>=23.0.0; extra == 'dev'
Requires-Dist: flake8>=7.0.0; extra == 'dev'
Requires-Dist: mypy>=1.8.0; extra == 'dev'
Requires-Dist: pytest-asyncio>=0.23.0; extra == 'dev'
Requires-Dist: pytest>=8.0.0; extra == 'dev'
